mockloop_mcp/__init__.py
mockloop_mcp/community_scenarios.py
mockloop_mcp/database_migration.py
mockloop_mcp/generator.py
mockloop_mcp/log_analyzer.py
mockloop_mcp/main.py
mockloop_mcp/mcp_audit_logger.py
mockloop_mcp/mcp_compliance.py
mockloop_mcp/mcp_context.py
mockloop_mcp/mcp_prompts.py
mockloop_mcp/mcp_resources.py
mockloop_mcp/mcp_tools.py
mockloop_mcp/mock_server_manager.py
mockloop_mcp/parser.py
mockloop_mcp/stdio_server.py
mockloop_mcp/proxy/__init__.py
mockloop_mcp/proxy/auth_handler.py
mockloop_mcp/proxy/config.py
mockloop_mcp/proxy/plugin_manager.py
mockloop_mcp/proxy/proxy_handler.py
mockloop_mcp/templates/admin_middleware_log_template.j2
mockloop_mcp/templates/admin_ui_template.j2
mockloop_mcp/templates/analytics_charts_template.j2
mockloop_mcp/templates/analytics_functions_template.j2
mockloop_mcp/templates/auth_middleware_template.j2
mockloop_mcp/templates/docker_compose_template.j2
mockloop_mcp/templates/dockerfile_template.j2
mockloop_mcp/templates/log_analyzer_template.j2
mockloop_mcp/templates/middleware_log_template.j2
mockloop_mcp/templates/route_template.j2
mockloop_mcp/templates/storage_template.j2
mockloop_mcp/templates/webhook_template.j2
mockloop_mcp/utils/__init__.py
mockloop_mcp/utils/http_client.py
mockloop_mcp-2.2.9.dist-info/licenses/LICENSE
mockloop_mcp-2.2.9.dist-info/METADATA
mockloop_mcp-2.2.9.dist-info/WHEEL
mockloop_mcp-2.2.9.dist-info/entry_points.txt
mockloop_mcp-2.2.9.dist-info/top_level.txt
mockloop_mcp-2.2.9.dist-info/RECORD
